README.md
setup.py
alba/__init__.py
alba.egg-info/PKG-INFO
alba.egg-info/SOURCES.txt
alba.egg-info/dependency_links.txt
alba.egg-info/top_level.txt