Metadata-Version: 2.1
Name: alba
Version: 0.1.0
Summary: ALBA controls meta package
Home-page: https://github.com/alba-synchrotron/alba
Author: ALBA Synchrotron computing team
Author-email: computing@cells.es
License: UNKNOWN
Keywords: ALBA,synchrotron,controls
Platform: UNKNOWN
Classifier: Development Status :: 2 - Pre-Alpha
Classifier: Intended Audience :: Developers
Classifier: Natural Language :: English
Classifier: Programming Language :: Python :: 3.5
Classifier: Programming Language :: Python :: 3.6
Classifier: Programming Language :: Python :: 3.7
Classifier: Programming Language :: Python :: 3.8
Classifier: License :: OSI Approved :: GNU General Public License v3 (GPLv3)
Requires-Python: >=3.5
